cmem_plugin_uuid/__init__.py
cmem_plugin_uuid/plugin_uuid.py
cmem_plugin_uuid/utils.py
cmem_plugin_uuid-2.0.0.dist-info/METADATA
cmem_plugin_uuid-2.0.0.dist-info/WHEEL
cmem_plugin_uuid-2.0.0.dist-info/licenses/LICENSE
cmem_plugin_uuid-2.0.0.dist-info/RECORD
