Metadata-Version: 2.4
Name: cmem-plugin-uuid
Version: 2.0.0
Summary: Create universally unique identifiers (UUIDs) versions 1, 3, 4, 5, 6, 7 and 8 in transformations.
License: Apache-2.0
License-File: LICENSE
Keywords: eccenca Corporate Memory,plugin,UUID
Author: eccenca GmbH
Author-email: cmempy-developer@eccenca.com
Requires-Python: >=3.13,<4.0
Classifier: Development Status :: 4 - Beta
Classifier: Environment :: Plugins
Classifier: License :: OSI Approved :: Apache Software License
Classifier: Programming Language :: Python :: 3
Classifier: Programming Language :: Python :: 3.13
Classifier: Programming Language :: Python :: 3.14
Requires-Dist: cmem-plugin-base (>=4.15.0,<5.0.0)
Requires-Dist: uuid6 (>=2024.7.10,<2025.0.0)
Project-URL: Homepage, https://github.com/eccenca/cmem-plugin-uuid
